strangeworks_azure/__init__.py
strangeworks_azure/backend.py
strangeworks_azure/job.py
strangeworks_azure-0.1.7.dist-info/METADATA
strangeworks_azure-0.1.7.dist-info/WHEEL
strangeworks_azure-0.1.7.dist-info/RECORD
