Metadata-Version: 2.4
Name: strangeworks-azure
Version: 0.1.7
Summary: 
Author: Strange Devs
Author-email: hello@strangeworks.com
Requires-Python: >=3.11,<4.0
Classifier: Programming Language :: Python :: 3
Classifier: Programming Language :: Python :: 3.11
Classifier: Programming Language :: Python :: 3.12
Classifier: Programming Language :: Python :: 3.13
Classifier: Programming Language :: Python :: 3.14
Requires-Dist: azure-quantum (>=3.5.0,<4.0.0)
Requires-Dist: qiskit (>=1.2.2,<2.0.0)
Requires-Dist: strangeworks (>=0.7.6,<0.8.0)
